mcp_error_codes/__init__.py
mcp_error_codes/error_bag.py
mcp_error_codes/error_code.py
mcp_error_codes/mcp_error.py
mcp_error_codes-1.0.0.dist-info/METADATA
mcp_error_codes-1.0.0.dist-info/WHEEL
mcp_error_codes-1.0.0.dist-info/licenses/LICENSE
mcp_error_codes-1.0.0.dist-info/RECORD
