Metadata-Version: 2.4
Name: mcp-error-codes
Version: 1.0.0
Summary: Standardized MCP error codes with semantic categories, HTTP/JSON-RPC mapping, and fluent builders
Project-URL: Homepage, https://github.com/code-wheel/mcp-error-codes-py
Project-URL: Repository, https://github.com/code-wheel/mcp-error-codes-py
Project-URL: Issues, https://github.com/code-wheel/mcp-error-codes-py/issues
Author: Code Wheel
License-Expression: MIT
License-File: LICENSE
Keywords: ai,error-codes,error-handling,json-rpc,llm,mcp,model-context-protocol
Classifier: Development Status :: 5 - Production/Stable
Classifier: Intended Audience :: Developers
Classifier: License :: OSI Approved :: MIT License
Classifier: Operating System :: OS Independent
Classifier: Programming Language :: Python :: 3
Classifier: Programming Language :: Python :: 3.10
Classifier: Programming Language :: Python :: 3.11
Classifier: Programming Language :: Python :: 3.12
Classifier: Programming Language :: Python :: 3.13
Classifier: Topic :: Software Development :: Libraries :: Python Modules
Classifier: Typing :: Typed
Requires-Python: >=3.10
Provides-Extra: dev
Requires-Dist: mypy>=1.0.0; extra == 'dev'
Requires-Dist: pytest-cov>=4.0.0; extra == 'dev'
Requires-Dist: pytest>=8.0.0; extra == 'dev'
Requires-Dist: ruff>=0.1.0; extra == 'dev'
Provides-Extra: mcp
Requires-Dist: mcp>=1.0.0; extra == 'mcp'
